pyroaddon/__init__.py
pyroaddon/filters/__init__.py
pyroaddon/filters/filters.py
pyroaddon/helpers/__init__.py
pyroaddon/helpers/helpers.py
pyroaddon/listen/__init__.py
pyroaddon/listen/listen.py
pyroaddon/message/__init__.py
pyroaddon/message/message.py
pyroaddon/nav/__init__.py
pyroaddon/nav/pagination.py
pyroaddon/utils/__init__.py
pyroaddon/utils/utils.py
pyroaddon-1.0.6.dist-info/LICENSE
pyroaddon-1.0.6.dist-info/METADATA
pyroaddon-1.0.6.dist-info/WHEEL
pyroaddon-1.0.6.dist-info/top_level.txt
pyroaddon-1.0.6.dist-info/RECORD
