Metadata-Version: 2.1
Name: pyroaddon
Version: 1.0.6
Summary: A monkeypatcher add-on for Pyrogram
Home-page: https://github.com/pyroaddon/pyroaddon
Author: pyroaddon
Author-email: pyroaddon@gmail.com
License: UNKNOWN
Project-URL: Bug Tracker, https://github.com/pyroaddon/pyroaddon/issues
Platform: UNKNOWN
Classifier: Programming Language :: Python :: 3
Classifier: License :: OSI Approved :: MIT License
Classifier: Operating System :: OS Independent
Requires-Python: >=3.6
License-File: LICENSE
